pina/__init__.py
pina/graph.py
pina/label_tensor.py
pina/operator.py
pina/trainer.py
pina/type_checker.py
pina/utils.py
pina/adaptive_function/__init__.py
pina/adaptive_function/adaptive_function.py
pina/adaptive_function/adaptive_function_interface.py
pina/callback/__init__.py
pina/callback/optim/switch_optimizer.py
pina/callback/optim/switch_scheduler.py
pina/callback/processing/metric_tracker.py
pina/callback/processing/normalizer_data_callback.py
pina/callback/processing/pina_progress_bar.py
pina/callback/refinement/__init__.py
pina/callback/refinement/r3_refinement.py
pina/callback/refinement/refinement_interface.py
pina/condition/__init__.py
pina/condition/condition.py
pina/condition/condition_interface.py
pina/condition/data_condition.py
pina/condition/domain_equation_condition.py
pina/condition/input_equation_condition.py
pina/condition/input_target_condition.py
pina/data/__init__.py
pina/data/data_module.py
pina/data/dataset.py
pina/domain/__init__.py
pina/domain/base_domain.py
pina/domain/base_operation.py
pina/domain/cartesian_domain.py
pina/domain/difference.py
pina/domain/domain_interface.py
pina/domain/ellipsoid_domain.py
pina/domain/exclusion.py
pina/domain/intersection.py
pina/domain/operation_interface.py
pina/domain/simplex_domain.py
pina/domain/union.py
pina/equation/__init__.py
pina/equation/equation.py
pina/equation/equation_factory.py
pina/equation/equation_interface.py
pina/equation/system_equation.py
pina/loss/__init__.py
pina/loss/linear_weighting.py
pina/loss/loss_interface.py
pina/loss/lp_loss.py
pina/loss/ntk_weighting.py
pina/loss/power_loss.py
pina/loss/scalar_weighting.py
pina/loss/self_adaptive_weighting.py
pina/loss/weighting_interface.py
pina/model/__init__.py
pina/model/average_neural_operator.py
pina/model/deeponet.py
pina/model/equivariant_graph_neural_operator.py
pina/model/feed_forward.py
pina/model/fourier_neural_operator.py
pina/model/graph_neural_operator.py
pina/model/kernel_neural_operator.py
pina_mathlab-0.2.6.post2602.dist-info/licenses/LICENSE.rst
pina_mathlab-0.2.6.post2602.dist-info/METADATA
pina_mathlab-0.2.6.post2602.dist-info/WHEEL
pina_mathlab-0.2.6.post2602.dist-info/top_level.txt
pina_mathlab-0.2.6.post2602.dist-info/RECORD
