Metadata-Version: 2.4
Name: pina-mathlab
Version: 0.2.6.post2602
Summary: Physic Informed Neural networks for Advance modeling.
Author-email: PINA Contributors <pina.mathlab@gmail.com>
License: MIT
Project-URL: Homepage, https://mathlab.github.io/PINA/
Project-URL: Repository, https://github.com/mathLab/PINA
Keywords: machine-learning,deep-learning,modeling,pytorch,ode,neural-networks,differential-equations,pde,hacktoberfest,pinn,physics-informed,physics-informed-neural-networks,neural-operators,equation-learning,lightining
Requires-Python: >=3.10
License-File: LICENSE.rst
Requires-Dist: torch
Requires-Dist: lightning
Requires-Dist: torch_geometric
Requires-Dist: matplotlib
Provides-Extra: doc
Requires-Dist: sphinx<8.2,>5.0; extra == "doc"
Requires-Dist: sphinx_rtd_theme; extra == "doc"
Requires-Dist: sphinx_copybutton; extra == "doc"
Requires-Dist: sphinx_design; extra == "doc"
Requires-Dist: pydata_sphinx_theme; extra == "doc"
Provides-Extra: test
Requires-Dist: pytest; extra == "test"
Requires-Dist: pytest-cov; extra == "test"
Requires-Dist: scipy; extra == "test"
Provides-Extra: dev
Requires-Dist: black; extra == "dev"
Provides-Extra: tutorial
Requires-Dist: jupyter; extra == "tutorial"
Requires-Dist: smithers; extra == "tutorial"
Requires-Dist: torchvision; extra == "tutorial"
Requires-Dist: tensorboard; extra == "tutorial"
Requires-Dist: scipy; extra == "tutorial"
Requires-Dist: numpy; extra == "tutorial"
Dynamic: license-file
